{
    "title": "Incrediwools",
    "subtitle": "Records for Incrediwools, a tournament hosted by Stratus Network",
    "page-category": ["tournaments", "league", "stratus"],
    "settings": {
        "include": {
            "scripts": [
                "/assets/js/tournaments-pages.js"
            ]
        },
        "tournaments": {
            "host": "stratus"
        }
    },
    "order": {
        "type": "Tournament",
        "number": 3,
        "last": "Attack on Point",
        "next": "Fullmetal Conquest"
    },
    "results": {
        "first_place": "Night Doobers",
        "second_place": "SK Telecom T1",
        "third_place": "Night ConnectionLost",
        "challonge": [
            {"url": "https://stratus.challonge.com/incrediwools", "description": "Invitational"}
        ]
    },
    "information": {
        "format": ["Qualifier (Group)", "Invitational (Double Elimination)"],
        "gamemodes": ["ctw"],
        "teams-count": "14 teams",
        "teamsize": "8v8",
        "stages": [
            {"stage": "Qualifier", "date": "August 11-12, 2018"},
            {"stage": "Invitational", "date": "August 18-19, 2018"}
        ]
    },
    "maps": [
        {
            "name": "Dead Heat",
            "slug": "dead_heat",
            "tags": ["blitz", "ctw"],
            "stage": "Vetoing Decider"
        },
        {
            "name": "Greenhouse",
            "slug": "greenhouse",
            "tags": ["blitz", "ctw"],
            "stage": "Tie Breaker"
        },
        {
            "name": "Clearcut TE",
            "slug": "clearcut",
            "tags": ["ctw"]
        },
        {
            "name": "Gobi",
            "slug": "gobi",
            "tags": ["ctw"]
        },
        {
            "name": "Safari",
            "slug": "safari",
            "tags": ["ctw"]
        },
        {
            "name": "Union",
            "slug": "union",
            "tags": ["ctw"]
        },
        {
            "name": "Wallop Too",
            "slug": "wallop_too",
            "tags": ["ctw"]
        }
    ],
    "teams": [
        {
            "name": "Qualifier",
            "advances": true,
            "groups": [
                {
                    "name": "Group A",
                    "teams": [
                        {"name": "Beaners"},
                        {"name": "GGeneSiS", "advances": true},
                        {"name": "Night Doobers", "advances": true},
                        {"name": "Obey"},
                        {"name": "PointecK", "advances": true},
                        {"name": "Tribe", "advances": true},
                        {"name": "UbeR"}
                    ]
                },
                {
                    "name": "Group B",
                    "teams": [
                        {"name": "Athene"},
                        {"name": "Casual Girl Gamers"},
                        {"name": "ConnectionLost", "advances": true},
                        {"name": "Fussion", "advances": true},
                        {"name": "SK Telecom T1", "advances": true},
                        {"name": "Stop Recycling", "advances": true},
                        {"name": "The Howards"}
                    ]
                }
            ]
        },
        {
            "name": "Invitational",
            "groups":[
                {
                    "name": "Invitational",
                    "teams": [
                        {"name": "ConnectionLost"},
                        {"name": "Fussion"},
                        {"name": "GGeneSiS"},
                        {"name": "Night Doobers"},
                        {"name": "PointecK"},
                        {"name": "SK Telecom T1"},
                        {"name": "Stop Recycling"},
                        {"name": "Tribe"}
                    ]
                }
            ]
        }
    ]
}
